{
  "id": "EPIC-001",
  "title": "",
  "description": "",
  "pipeline": "sdlc-parallel-full",
  "agent": null,
  "agents": [
    "aidlc-po",
    "aidlc-tech-lead",
    "aidlc-qa",
    "aidlc-developer",
    "aidlc-qa",
    "aidlc-qa",
    "aidlc-release-manager",
    "aidlc-archivist"
  ],
  "currentStep": 0,
  "status": "in_progress",
  "createdAt": "2026-05-22T01:57:03.076Z",
  "stepStates": [
    {
      "agent": "aidlc-po",
      "status": "in_progress",
      "revision": 1,
      "runStatus": "awaiting_work",
      "startedAt": "2026-05-22T01:57:03.083Z",
      "finishedAt": null,
      "history": [],
      "artifactsProduced": []
    },
    {
      "agent": "aidlc-tech-lead",
      "status": "pending",
      "revision": 1,
      "runStatus": "pending",
      "startedAt": null,
      "finishedAt": null,
      "history": [],
      "artifactsProduced": []
    },
    {
      "agent": "aidlc-qa",
      "status": "pending",
      "revision": 1,
      "runStatus": "pending",
      "startedAt": null,
      "finishedAt": null,
      "history": [],
      "artifactsProduced": []
    },
    {
      "agent": "aidlc-developer",
      "status": "pending",
      "revision": 1,
      "runStatus": "pending",
      "startedAt": null,
      "finishedAt": null,
      "history": [],
      "artifactsProduced": []
    },
    {
      "agent": "aidlc-qa",
      "status": "pending",
      "revision": 1,
      "runStatus": "pending",
      "startedAt": null,
      "finishedAt": null,
      "history": [],
      "artifactsProduced": []
    },
    {
      "agent": "aidlc-qa",
      "status": "pending",
      "revision": 1,
      "runStatus": "pending",
      "startedAt": null,
      "finishedAt": null,
      "history": [],
      "artifactsProduced": []
    },
    {
      "agent": "aidlc-release-manager",
      "status": "pending",
      "revision": 1,
      "runStatus": "pending",
      "startedAt": null,
      "finishedAt": null,
      "history": [],
      "artifactsProduced": []
    },
    {
      "agent": "aidlc-archivist",
      "status": "pending",
      "revision": 1,
      "runStatus": "pending",
      "startedAt": null,
      "finishedAt": null,
      "history": [],
      "artifactsProduced": []
    }
  ],
  "updatedAt": "2026-05-22T01:57:03.085Z"
}
